pyqueued.py
setup.py
pyqueued.egg-info/PKG-INFO
pyqueued.egg-info/SOURCES.txt
pyqueued.egg-info/dependency_links.txt
pyqueued.egg-info/requires.txt
pyqueued.egg-info/top_level.txt