Metadata-Version: 1.0
Name: pyqueued
Version: 0.1.4
Summary: A client for queued.
Home-page: https://github.com/miku/pyqueued
Author: Martin Czygan
Author-email: martin.czygan@gmail.com
License: UNKNOWN
Platform: UNKNOWN
